Workbook

Sheet learn
C4: Pivot Table | D4: Pivot Table | E4: Pivot Table | F4: Pivot Table | G4: Pivot Table | H4: Pivot Table | I4: Pivot Table | J4: Pivot Table | K4: Pivot Table | L4: Pivot Table | M4: Pivot Table | N4: Pivot Table | O4: Pivot Table | P4: Pivot Table | Q4: Pivot Table | R4: Pivot Table | S4: Pivot Table | T4: Pivot Table | U4: Pivot Table | V4: Pivot Table | W4: Pivot Table | X4: Pivot Table
C5: Pivot Table
C6: Pivot Table
C7: Pivot Table
C8: Pivot Table
C9: Pivot Table
C10: Pivot Table
C11: Pivot Table
C12: Pivot Table
C13: Pivot Table
C14: Pivot Table
C15: Pivot Table
C16: Pivot Table
... C92: Pivot Table

Sheet if
F3: Result Calc
G4: Less Then | H4: Greter then | L4: Less Then Equal | M4: Greter then equal | N4: Not equal | O4: Equal
F5: IF | G5: < | H5: > | L5: <= | M5: >= | N5: <> | O5: =
F6: Name | G6: Marks | H6: Pass Marks | L6: Pass <= | M6: Fail >=
F7: a | G7: 33 | H7: 33 | L7: =IF(G7>=H7,"Pass",) -> Pass | M7: =IF(H7<=L7,0,"Fail") -> 0
F8: b | G8: 34 | H8: 33 | L8: =IF(G8>=H8,"Pass",) -> Pass | M8: =IF(H8<=L8,0,"Fail") -> 0
F9: c | G9: 32 | H9: 33 | L9: =IF(G9>=H9,"Pass",) -> 0 | M9: =IF(H9<=L9,0,"Fail") -> Fail
F10: d | G10: 30 | H10: 33 | L10: =IF(G10>=H10,"Pass",) -> 0 | M10: =IF(H10<=L10,0,"Fail") -> Fail
F11: e | G11: 40 | H11: 33 | L11: =IF(G11>=H11,"Pass",) -> Pass | M11: =IF(H11<=L11,0,"Fail") -> 0
F12: f | G12: 50 | H12: 33 | L12: =IF(G12>=H12,"Pass",) -> Pass | M12: =IF(H12<=L12,0,"Fail") -> 0
F13: g | G13: 55 | H13: 33 | L13: =IF(G13>=H13,"Pass",) -> Pass | M13: =IF(H13<=L13,0,"Fail") -> 0
F14: h | G14: 60 | H14: 33 | L14: =IF(G14>=H14,"Pass",) -> Pass | M14: =IF(H14<=L14,0,"Fail") -> 0
F20: SL | G20: ID | H20: Name | I20: Bangla | J20: Math | K20: English | L20: Marks | M20: Grade | N20: Result
F21: 1 | G21: 1281148 | H21: MD. SANAULLA | L21: 100 | M21: =IF(L21<=32,"F",IF(L21<=39,"D",IF(L21<=49,"C",IF(L21<=59,"B",IF(L21<=69,"A-",IF(L21<=79,"A","A+")))))) -> A+ | P21: 0-32 | Q21: F
F22: 2 | G22: 1281250 | H22: MD. RAJU AHMED | L22: 51 | M22: =IF(L22<=32,"F",IF(L22<=39,"D",IF(L22<=49,"C",IF(L22<=59,"B",IF(L22<=69,"A-",IF(L22<=79,"A","A+")))))) -> B | P22: 33-39 | Q22: D
F23: 3 | G23: 1281305 | H23: Md Najmul Islam | L23: 57 | M23: =IF(L23<=32,"F",IF(L23<=39,"D",IF(L23<=49,"C",IF(L23<=59,"B",IF(L23<=69,"A-",IF(L23<=79,"A","A+")))))) -> B | P23: 40-49 | Q23: C
F24: 4 | G24: 1281332 | H24: Mostofa Aminur Rashid | L24: 96 | M24: =IF(L24<=32,"F",IF(L24<=39,"D",IF(L24<=49,"C",IF(L24<=59,"B",IF(L24<=69,"A-",IF(L24<=79,"A","A+")))))) -> A+ | P24: 50-59 | Q24: B
F25: 5 | G25: 1281514 | H25: Md.Kutub Uddin | L25: 79 | M25: =IF(L25<=32,"F",IF(L25<=39,"D",IF(L25<=49,"C",IF(L25<=59,"B",IF(L25<=69,"A-",IF(L25<=79,"A","A+")))))) -> A | P25: 60-69 | Q25: A-
F26: 6 | G26: 1281521 | H26: Shamima Nasrin | L26: 37 | M26: =IF(L26<=32,"F",IF(L26<=39,"D",IF(L26<=49,"C",IF(L26<=59,"B",IF(L26<=69,"A-",IF(L26<=79,"A","A+")))))) -> D | P26: 70-79 | Q26: A
F27: 7 | G27: 1281524 | H27: Md. Towhidul Alam | L27: 61 | M27: =IF(L27<=32,"F",IF(L27<=39,"D",IF(L27<=49,"C",IF(L27<=59,"B",IF(L27<=69,"A-",IF(L27<=79,"A","A+")))))) -> A- | P27: 80-100 | Q27: A+
F28: 8 | G28: 1281525 | H28: MD. AMINUL HOQUE | L28: 22 | M28: =IF(L28<=32,"F",IF(L28<=39,"D",IF(L28<=49,"C",IF(L28<=59,"B",IF(L28<=69,"A-",IF(L28<=79,"A","A+")))))) -> F
F29: 9 | G29: 1281539 | H29: Shabab Ahmed | L29: 46 | M29: =IF(L29<=32,"F",IF(L29<=39,"D",IF(L29<=49,"C",IF(L29<=59,"B",IF(L29<=69,"A-",IF(L29<=79,"A","A+")))))) -> C
F30: 10 | G30: 1281573 | H30: Md. Rabiul Islam | L30: 69 | M30: =IF(L30<=32,"F",IF(L30<=39,"D",IF(L30<=49,"C",IF(L30<=59,"B",IF(L30<=69,"A-",IF(L30<=79,"A","A+")))))) -> A-
F31: 11 | G31: 1281608 | H31: Nusrat Jahan | L31: 25 | M31: =IF(L31<=32,"F",IF(L31<=39,"D",IF(L31<=49,"C",IF(L31<=59,"B",IF(L31<=69,"A-",IF(L31<=79,"A","A+")))))) -> F
F32: 12 | G32: 1281656 | H32: MD. RAFIQUL ISLAM RAZU | L32: 46 | M32: =IF(L32<=32,"F",IF(L32<=39,"D",IF(L32<=49,"C",IF(L32<=59,"B",IF(L32<=69,"A-",IF(L32<=79,"A","A+")))))) -> C
F33: 13 | G33: 1281661 | H33: MD. Nasif Shahriar | L33: 79 | M33: =IF(L33<=32,"F",IF(L33<=39,"D",IF(L33<=49,"C",IF(L33<=59,"B",IF(L33<=69,"A-",IF(L33<=79,"A","A+")))))) -> A
F34: 14 | G34: 1281714 | H34: Hasan | L34: 86 | M34: =IF(L34<=32,"F",IF(L34<=39,"D",IF(L34<=49,"C",IF(L34<=59,"B",IF(L34<=69,"A-",IF(L34<=79,"A","A+")))))) -> A+
F35: 15 | G35: 1281745 | H35: NAYAMUL LSLAM | L35: 58 | M35: =IF(L35<=32,"F",IF(L35<=39,"D",IF(L35<=49,"C",IF(L35<=59,"B",IF(L35<=69,"A-",IF(L35<=79,"A","A+")))))) -> B

Sheet vlookup
N7: Column1 | O7: Column2 | P7: Column3 | Q7: Column4 | R7: Column5 | S7: Column6 | T7: Column7 | U7: Column8 | V7: Column9
N8: Order No | O8: Customer Name | P8: Total | Q8: City | R8: State | S8: Customer Type | T8: Account Manager | U8: Order Priority | V8: Product Name
N9: 5071-1 | O9: =VLOOKUP(N9,[1]Orders!$A$5:$W$1043,3,0) -> Christopher Schild | P9: =VLOOKUP(N9,[1]Orders!$A$5:$W$1043,23,0) -> 335.69 | Q9: =VLOOKUP(N9,[1]Orders!$A$5:$W$1043,5,0) -> Sydney | R9: =VLOOKUP(N9,[1]Orders!$A$5:$W$1043,5,0) -> Sydney | S9: =VLOOKUP(N9,[1]Orders!$A$5:$W$1043,6,0) -> NSW | T9: =VLOOKUP(N9,[1]Orders!$A$5:$W$1043,7,0) -> Corporate | U9: =VLOOKUP(N9,[1]Orders!$A$5:$W$1043,8,0) -> Tina Carlton | V9: =VLOOKUP(N9,[1]Orders!$A$5:$W$1043,9,0) -> Medium
N10: 5071-2 | O10: =VLOOKUP(N10,[1]Orders!$A$5:$W$1043,3,0) -> Christopher Schild | P10: =VLOOKUP(N10,[1]Orders!$A$5:$W$1043,23,0) -> 14.85 | Q10: =VLOOKUP(N10,[1]Orders!$A$5:$W$1043,5,0) -> Sydney | R10: =VLOOKUP(N10,[1]Orders!$A$5:$W$1043,5,0) -> Sydney | S10: =VLOOKUP(N10,[1]Orders!$A$5:$W$1043,6,0) -> NSW | T10: =VLOOKUP(N10,[1]Orders!$A$5:$W$1043,7,0) -> Corporate | U10: =VLOOKUP(N10,[1]Orders!$A$5:$W$1043,8,0) -> Tina Carlton | V10: =VLOOKUP(N10,[1]Orders!$A$5:$W$1043,9,0) -> Medium
N11: 5145-1 | O11: =VLOOKUP(N11,[1]Orders!$A$5:$W$1043,3,0) -> Cyma Kinney | P11: =VLOOKUP(N11,[1]Orders!$A$5:$W$1043,23,0) -> 7.2 | Q11: =VLOOKUP(N11,[1]Orders!$A$5:$W$1043,5,0) -> Sydney | R11: =VLOOKUP(N11,[1]Orders!$A$5:$W$1043,5,0) -> Sydney | S11: =VLOOKUP(N11,[1]Orders!$A$5:$W$1043,6,0) -> NSW | T11: =VLOOKUP(N11,[1]Orders!$A$5:$W$1043,7,0) -> Small Business | U11: =VLOOKUP(N11,[1]Orders!$A$5:$W$1043,8,0) -> Phoebe Gour | V11: =VLOOKUP(N11,[1]Orders!$A$5:$W$1043,9,0) -> Low
N12: 5145-2 | O12: =VLOOKUP(N12,[1]Orders!$A$5:$W$1043,3,0) -> Cyma Kinney | P12: =VLOOKUP(N12,[1]Orders!$A$5:$W$1043,23,0) -> 24.1 | Q12: =VLOOKUP(N12,[1]Orders!$A$5:$W$1043,5,0) -> Sydney | R12: =VLOOKUP(N12,[1]Orders!$A$5:$W$1043,5,0) -> Sydney | S12: =VLOOKUP(N12,[1]Orders!$A$5:$W$1043,6,0) -> NSW | T12: =VLOOKUP(N12,[1]Orders!$A$5:$W$1043,7,0) -> Small Business | U12: =VLOOKUP(N12,[1]Orders!$A$5:$W$1043,8,0) -> Phoebe Gour | V12: =VLOOKUP(N12,[1]Orders!$A$5:$W$1043,9,0) -> Low
N13: 5160-1 | O13: =VLOOKUP(N13,[1]Orders!$A$5:$W$1043,3,0) -> Berenike Kampe | P13: =VLOOKUP(N13,[1]Orders!$A$5:$W$1043,23,0) -> 865.38 | Q13: =VLOOKUP(N13,[1]Orders!$A$5:$W$1043,5,0) -> Melbourne | R13: =VLOOKUP(N13,[1]Orders!$A$5:$W$1043,5,0) -> Melbourne | S13: =VLOOKUP(N13,[1]Orders!$A$5:$W$1043,6,0) -> VIC | T13: =VLOOKUP(N13,[1]Orders!$A$5:$W$1043,7,0) -> Corporate | U13: =VLOOKUP(N13,[1]Orders!$A$5:$W$1043,8,0) -> Connor Betts | V13: =VLOOKUP(N13,[1]Orders!$A$5:$W$1043,9,0) -> Not Specified
N14: 5160-2 | O14: =VLOOKUP(N14,[1]Orders!$A$5:$W$1043,3,0) -> Berenike Kampe | P14: =VLOOKUP(N14,[1]Orders!$A$5:$W$1043,23,0) -> 148.13 | Q14: =VLOOKUP(N14,[1]Orders!$A$5:$W$1043,5,0) -> Melbourne | R14: =VLOOKUP(N14,[1]Orders!$A$5:$W$1043,5,0) -> Melbourne | S14: =VLOOKUP(N14,[1]Orders!$A$5:$W$1043,6,0) -> VIC | T14: =VLOOKUP(N14,[1]Orders!$A$5:$W$1043,7,0) -> Corporate | U14: =VLOOKUP(N14,[1]Orders!$A$5:$W$1043,8,0) -> Connor Betts | V14: =VLOOKUP(N14,[1]Orders!$A$5:$W$1043,9,0) -> Not Specified
N15: 5168-1 | O15: =VLOOKUP(N15,[1]Orders!$A$5:$W$1043,3,0) -> Christy Brittain | P15: =VLOOKUP(N15,[1]Orders!$A$5:$W$1043,23,0) -> 130.6 | Q15: =VLOOKUP(N15,[1]Orders!$A$5:$W$1043,5,0) -> Sydney | R15: =VLOOKUP(N15,[1]Orders!$A$5:$W$1043,5,0) -> Sydney | S15: =VLOOKUP(N15,[1]Orders!$A$5:$W$1043,6,0) -> NSW | T15: =VLOOKUP(N15,[1]Orders!$A$5:$W$1043,7,0) -> Consumer | U15: =VLOOKUP(N15,[1]Orders!$A$5:$W$1043,8,0) -> Mihael Khan | V15: =VLOOKUP(N15,[1]Orders!$A$5:$W$1043,9,0) -> Critical
N16: 5168-2 | O16: =VLOOKUP(N16,[1]Orders!$A$5:$W$1043,3,0) -> Christy Brittain | P16: =VLOOKUP(N16,[1]Orders!$A$5:$W$1043,23,0) -> 111.62 | Q16: =VLOOKUP(N16,[1]Orders!$A$5:$W$1043,5,0) -> Sydney | R16: =VLOOKUP(N16,[1]Orders!$A$5:$W$1043,5,0) -> Sydney | S16: =VLOOKUP(N16,[1]Orders!$A$5:$W$1043,6,0) -> NSW | T16: =VLOOKUP(N16,[1]Orders!$A$5:$W$1043,7,0) -> Consumer | U16: =VLOOKUP(N16,[1]Orders!$A$5:$W$1043,8,0) -> Mihael Khan | V16: =VLOOKUP(N16,[1]Orders!$A$5:$W$1043,9,0) -> Critical
N17: 5195-1 | O17: =VLOOKUP(N17,[1]Orders!$A$5:$W$1043,3,0) -> Alex Grayson | P17: =VLOOKUP(N17,[1]Orders!$A$5:$W$1043,23,0) -> 33.08 | Q17: =VLOOKUP(N17,[1]Orders!$A$5:$W$1043,5,0) -> Sydney | R17: =VLOOKUP(N17,[1]Orders!$A$5:$W$1043,5,0) -> Sydney | S17: =VLOOKUP(N17,[1]Orders!$A$5:$W$1043,6,0) -> NSW | T17: =VLOOKUP(N17,[1]Orders!$A$5:$W$1043,7,0) -> Consumer | U17: =VLOOKUP(N17,[1]Orders!$A$5:$W$1043,8,0) -> Radhya Staples | V17: =VLOOKUP(N17,[1]Orders!$A$5:$W$1043,9,0) -> Medium
B18: Order No | C18: Customer Name | D18: Total | E18: City | F18: State | G18: Customer Type | H18: Account Manager | I18: Order Priority | J18: Product Name | N18: 5195-2 | O18: =VLOOKUP(N18,[1]Orders!$A$5:$W$1043,3,0) -> Alex Grayson | P18: =VLOOKUP(N18,[1]Orders!$A$5:$W$1043,23,0) -> 863.04 | Q18: =VLOOKUP(N18,[1]Orders!$A$5:$W$1043,5,0) -> Sydney | R18: =VLOOKUP(N18,[1]Orders!$A$5:$W$1043,5,0) -> Sydney | S18: =VLOOKUP(N18,[1]Orders!$A$5:$W$1043,6,0) -> NSW | T18: =VLOOKUP(N18,[1]Orders!$A$5:$W$1043,7,0) -> Consumer | U18: =VLOOKUP(N18,[1]Orders!$A$5:$W$1043,8,0) -> Radhya Staples | V18: =VLOOKUP(N18,[1]Orders!$A$5:$W$1043,9,0) -> Medium
B19: 5071-1 | C19: =VLOOKUP(B19,data[],2,0) -> Christopher Schild | D19: =VLOOKUP(B19,data[],3,0) -> 335.69 | E19: =VLOOKUP(B19,data[],4,0) -> Sydney | F19: =VLOOKUP(B19,data[],5,0) -> Sydney | G19: =VLOOKUP(B19,data[],6,0) -> NSW | H19: =VLOOKUP(B19,data[],7,0) -> Corporate | I19: =VLOOKUP(B19,data[],8,0) -> Tina Carlton | J19: =VLOOKUP(B19,data[],9,0) -> Medium | N19: 5268-1 | O19: =VLOOKUP(N19,[1]Orders!$A$5:$W$1043,3,0) -> Stephanie Ulpright | P19: =VLOOKUP(N19,[1]Orders!$A$5:$W$1043,23,0) -> 14.72 | Q19: =VLOOKUP(N19,[1]Orders!$A$5:$W$1043,5,0) -> Melbourne | R19: =VLOOKUP(N19,[1]Orders!$A$5:$W$1043,5,0) -> Melbourne | S19: =VLOOKUP(N19,[1]Orders!$A$5:$W$1043,6,0) -> VIC | T19: =VLOOKUP(N19,[1]Orders!$A$5:$W$1043,7,0) -> Consumer | U19: =VLOOKUP(N19,[1]Orders!$A$5:$W$1043,8,0) -> Yvette Biti | V19: =VLOOKUP(N19,[1]Orders!$A$5:$W$1043,9,0) -> Not Specified
B20: 5071-2 | C20: =VLOOKUP(B20,data[],2,0) -> Christopher Schild | D20: =VLOOKUP(B20,data[],3,0) -> 14.85 | E20: =VLOOKUP(B20,data[],4,0) -> Sydney | F20: =VLOOKUP(B20,data[],5,0) -> Sydney | G20: =VLOOKUP(B20,data[],6,0) -> NSW | H20: =VLOOKUP(B20,data[],7,0) -> Corporate | I20: =VLOOKUP(B20,data[],8,0) -> Tina Carlton | J20: =VLOOKUP(B20,data[],9,0) -> Medium | N20: 5268-2 | O20: =VLOOKUP(N20,[1]Orders!$A$5:$W$1043,3,0) -> Stephanie Ulpright | P20: =VLOOKUP(N20,[1]Orders!$A$5:$W$1043,23,0) -> 1011.1 | Q20: =VLOOKUP(N20,[1]Orders!$A$5:$W$1043,5,0) -> Melbourne | R20: =VLOOKUP(N20,[1]Orders!$A$5:$W$1043,5,0) -> Melbourne | S20: =VLOOKUP(N20,[1]Orders!$A$5:$W$1043,6,0) -> VIC | T20: =VLOOKUP(N20,[1]Orders!$A$5:$W$1043,7,0) -> Consumer | U20: =VLOOKUP(N20,[1]Orders!$A$5:$W$1043,8,0) -> Yvette Biti | V20: =VLOOKUP(N20,[1]Orders!$A$5:$W$1043,9,0) -> Not Specified
B21: 5145-1 | C21: =VLOOKUP(B21,data[],2,0) -> Cyma Kinney | D21: =VLOOKUP(B21,data[],3,0) -> 7.2 | E21: =VLOOKUP(B21,data[],4,0) -> Sydney | F21: =VLOOKUP(B21,data[],5,0) -> Sydney | G21: =VLOOKUP(B21,data[],6,0) -> NSW | H21: =VLOOKUP(B21,data[],7,0) -> Small Business | I21: =VLOOKUP(B21,data[],8,0) -> Phoebe Gour | J21: =VLOOKUP(B21,data[],9,0) -> Low
B22: 5145-2 | C22: =VLOOKUP(B22,data[],2,0) -> Cyma Kinney | D22: =VLOOKUP(B22,data[],3,0) -> 24.1 | E22: =VLOOKUP(B22,data[],4,0) -> Sydney | F22: =VLOOKUP(B22,data[],5,0) -> Sydney | G22: =VLOOKUP(B22,data[],6,0) -> NSW | H22: =VLOOKUP(B22,data[],7,0) -> Small Business | I22: =VLOOKUP(B22,data[],8,0) -> Phoebe Gour | J22: =VLOOKUP(B22,data[],9,0) -> Low
B23: 5160-1 | C23: =VLOOKUP(B23,data[],2,0) -> Berenike Kampe | D23: =VLOOKUP(B23,data[],3,0) -> 865.38 | E23: =VLOOKUP(B23,data[],4,0) -> Melbourne | F23: =VLOOKUP(B23,data[],5,0) -> Melbourne | G23: =VLOOKUP(B23,data[],6,0) -> VIC | H23: =VLOOKUP(B23,data[],7,0) -> Corporate | I23: =VLOOKUP(B23,data[],8,0) -> Connor Betts | J23: =VLOOKUP(B23,data[],9,0) -> Not Specified
B24: 5160-2 | C24: =VLOOKUP(B24,data[],2,0) -> Berenike Kampe | D24: =VLOOKUP(B24,data[],3,0) -> 148.13 | E24: =VLOOKUP(B24,data[],4,0) -> Melbourne | F24: =VLOOKUP(B24,data[],5,0) -> Melbourne | G24: =VLOOKUP(B24,data[],6,0) -> VIC | H24: =VLOOKUP(B24,data[],7,0) -> Corporate | I24: =VLOOKUP(B24,data[],8,0) -> Connor Betts | J24: =VLOOKUP(B24,data[],9,0) -> Not Specified
B25: 5168-1 | C25: =VLOOKUP(B25,data[],2,0) -> Christy Brittain | D25: =VLOOKUP(B25,data[],3,0) -> 130.6 | E25: =VLOOKUP(B25,data[],4,0) -> Sydney | F25: =VLOOKUP(B25,data[],5,0) -> Sydney | G25: =VLOOKUP(B25,data[],6,0) -> NSW | H25: =VLOOKUP(B25,data[],7,0) -> Consumer | I25: =VLOOKUP(B25,data[],8,0) -> Mihael Khan | J25: =VLOOKUP(B25,data[],9,0) -> Critical
B26: 5168-2 | C26: =VLOOKUP(B26,data[],2,0) -> Christy Brittain | D26: =VLOOKUP(B26,data[],3,0) -> 111.62 | E26: =VLOOKUP(B26,data[],4,0) -> Sydney | F26: =VLOOKUP(B26,data[],5,0) -> Sydney | G26: =VLOOKUP(B26,data[],6,0) -> NSW | H26: =VLOOKUP(B26,data[],7,0) -> Consumer | I26: =VLOOKUP(B26,data[],8,0) -> Mihael Khan | J26: =VLOOKUP(B26,data[],9,0) -> Critical
B27: 5195-1 | C27: =VLOOKUP(B27,data[],2,0) -> Alex Grayson | D27: =VLOOKUP(B27,data[],3,0) -> 33.08 | E27: =VLOOKUP(B27,data[],4,0) -> Sydney | F27: =VLOOKUP(B27,data[],5,0) -> Sydney | G27: =VLOOKUP(B27,data[],6,0) -> NSW | H27: =VLOOKUP(B27,data[],7,0) -> Consumer | I27: =VLOOKUP(B27,data[],8,0) -> Radhya Staples | J27: =VLOOKUP(B27,data[],9,0) -> Medium
B28: 5195-2 | C28: =VLOOKUP(B28,data[],2,0) -> Alex Grayson | D28: =VLOOKUP(B28,data[],3,0) -> 863.04 | E28: =VLOOKUP(B28,data[],4,0) -> Sydney | F28: =VLOOKUP(B28,data[],5,0) -> Sydney | G28: =VLOOKUP(B28,data[],6,0) -> NSW | H28: =VLOOKUP(B28,data[],7,0) -> Consumer | I28: =VLOOKUP(B28,data[],8,0) -> Radhya Staples | J28: =VLOOKUP(B28,data[],9,0) -> Medium
B29: 5268-1 | C29: =VLOOKUP(B29,data[],2,0) -> Stephanie Ulpright | D29: =VLOOKUP(B29,data[],3,0) -> 14.72 | E29: =VLOOKUP(B29,data[],4,0) -> Melbourne | F29: =VLOOKUP(B29,data[],5,0) -> Melbourne | G29: =VLOOKUP(B29,data[],6,0) -> VIC | H29: =VLOOKUP(B29,data[],7,0) -> Consumer | I29: =VLOOKUP(B29,data[],8,0) -> Yvette Biti | J29: =VLOOKUP(B29,data[],9,0) -> Not Specified
B30: 5268-2 | C30: =VLOOKUP(B30,data[],2,0) -> Stephanie Ulpright | D30: =VLOOKUP(B30,data[],3,0) -> 1011.1 | E30: =VLOOKUP(B30,data[],4,0) -> Melbourne | F30: =VLOOKUP(B30,data[],5,0) -> Melbourne | G30: =VLOOKUP(B30,data[],6,0) -> VIC | H30: =VLOOKUP(B30,data[],7,0) -> Consumer | I30: =VLOOKUP(B30,data[],8,0) -> Yvette Biti | J30: =VLOOKUP(B30,data[],9,0) -> Not Specified

Sheet data
C5: Order No | D5: Customer Name | E5: Total | F5: City | G5: State | H5: Customer Type | I5: Account Manager | J5: Order Priority | K5: Product Name
C6: 5071-1 | D6: =VLOOKUP(C6,[1]Orders!$A$5:$W$1043,3,0) -> Christopher Schild | E6: =VLOOKUP(C6,[1]Orders!$A$5:$W$1043,23,0) -> 335.69 | F6: =VLOOKUP(C6,[1]Orders!$A$5:$W$1043,5,0) -> Sydney | G6: =VLOOKUP(C6,[1]Orders!$A$5:$W$1043,5,0) -> Sydney | H6: =VLOOKUP(C6,[1]Orders!$A$5:$W$1043,6,0) -> NSW | I6: =VLOOKUP(C6,[1]Orders!$A$5:$W$1043,7,0) -> Corporate | J6: =VLOOKUP(C6,[1]Orders!$A$5:$W$1043,8,0) -> Tina Carlton | K6: =VLOOKUP(C6,[1]Orders!$A$5:$W$1043,9,0) -> Medium
C7: 5071-2 | D7: =VLOOKUP(C7,[1]Orders!$A$5:$W$1043,3,0) -> Christopher Schild | E7: =VLOOKUP(C7,[1]Orders!$A$5:$W$1043,23,0) -> 14.85 | F7: =VLOOKUP(C7,[1]Orders!$A$5:$W$1043,5,0) -> Sydney | G7: =VLOOKUP(C7,[1]Orders!$A$5:$W$1043,5,0) -> Sydney | H7: =VLOOKUP(C7,[1]Orders!$A$5:$W$1043,6,0) -> NSW | I7: =VLOOKUP(C7,[1]Orders!$A$5:$W$1043,7,0) -> Corporate | J7: =VLOOKUP(C7,[1]Orders!$A$5:$W$1043,8,0) -> Tina Carlton | K7: =VLOOKUP(C7,[1]Orders!$A$5:$W$1043,9,0) -> Medium
C8: 5145-1 | D8: =VLOOKUP(C8,[1]Orders!$A$5:$W$1043,3,0) -> Cyma Kinney | E8: =VLOOKUP(C8,[1]Orders!$A$5:$W$1043,23,0) -> 7.2 | F8: =VLOOKUP(C8,[1]Orders!$A$5:$W$1043,5,0) -> Sydney | G8: =VLOOKUP(C8,[1]Orders!$A$5:$W$1043,5,0) -> Sydney | H8: =VLOOKUP(C8,[1]Orders!$A$5:$W$1043,6,0) -> NSW | I8: =VLOOKUP(C8,[1]Orders!$A$5:$W$1043,7,0) -> Small Business | J8: =VLOOKUP(C8,[1]Orders!$A$5:$W$1043,8,0) -> Phoebe Gour | K8: =VLOOKUP(C8,[1]Orders!$A$5:$W$1043,9,0) -> Low | N8: city | O8: c type
C9: 5145-2 | D9: =VLOOKUP(C9,[1]Orders!$A$5:$W$1043,3,0) -> Cyma Kinney | E9: =VLOOKUP(C9,[1]Orders!$A$5:$W$1043,23,0) -> 24.1 | F9: =VLOOKUP(C9,[1]Orders!$A$5:$W$1043,5,0) -> Sydney | G9: =VLOOKUP(C9,[1]Orders!$A$5:$W$1043,5,0) -> Sydney | H9: =VLOOKUP(C9,[1]Orders!$A$5:$W$1043,6,0) -> NSW | I9: =VLOOKUP(C9,[1]Orders!$A$5:$W$1043,7,0) -> Small Business | J9: =VLOOKUP(C9,[1]Orders!$A$5:$W$1043,8,0) -> Phoebe Gour | K9: =VLOOKUP(C9,[1]Orders!$A$5:$W$1043,9,0) -> Low | N9: Sydney | O9: Corporate
C10: 5160-1 | D10: =VLOOKUP(C10,[1]Orders!$A$5:$W$1043,3,0) -> Berenike Kampe | E10: =VLOOKUP(C10,[1]Orders!$A$5:$W$1043,23,0) -> 865.38 | F10: =VLOOKUP(C10,[1]Orders!$A$5:$W$1043,5,0) -> Melbourne | G10: =VLOOKUP(C10,[1]Orders!$A$5:$W$1043,5,0) -> Melbourne | H10: =VLOOKUP(C10,[1]Orders!$A$5:$W$1043,6,0) -> VIC | I10: =VLOOKUP(C10,[1]Orders!$A$5:$W$1043,7,0) -> Corporate | J10: =VLOOKUP(C10,[1]Orders!$A$5:$W$1043,8,0) -> Connor Betts | K10: =VLOOKUP(C10,[1]Orders!$A$5:$W$1043,9,0) -> Not Specified | N10: Melbourne | O10: Small Business
C11: 5160-2 | D11: =VLOOKUP(C11,[1]Orders!$A$5:$W$1043,3,0) -> Berenike Kampe | E11: =VLOOKUP(C11,[1]Orders!$A$5:$W$1043,23,0) -> 148.13 | F11: =VLOOKUP(C11,[1]Orders!$A$5:$W$1043,5,0) -> Melbourne | G11: =VLOOKUP(C11,[1]Orders!$A$5:$W$1043,5,0) -> Melbourne | H11: =VLOOKUP(C11,[1]Orders!$A$5:$W$1043,6,0) -> VIC | I11: =VLOOKUP(C11,[1]Orders!$A$5:$W$1043,7,0) -> Corporate | J11: =VLOOKUP(C11,[1]Orders!$A$5:$W$1043,8,0) -> Connor Betts | K11: =VLOOKUP(C11,[1]Orders!$A$5:$W$1043,9,0) -> Not Specified | O11: Consumer
C12: 5168-1 | D12: =VLOOKUP(C12,[1]Orders!$A$5:$W$1043,3,0) -> Christy Brittain | E12: =VLOOKUP(C12,[1]Orders!$A$5:$W$1043,23,0) -> 130.6 | F12: =VLOOKUP(C12,[1]Orders!$A$5:$W$1043,5,0) -> Sydney | G12: =VLOOKUP(C12,[1]Orders!$A$5:$W$1043,5,0) -> Sydney | H12: =VLOOKUP(C12,[1]Orders!$A$5:$W$1043,6,0) -> NSW | I12: =VLOOKUP(C12,[1]Orders!$A$5:$W$1043,7,0) -> Consumer | J12: =VLOOKUP(C12,[1]Orders!$A$5:$W$1043,8,0) -> Mihael Khan | K12: =VLOOKUP(C12,[1]Orders!$A$5:$W$1043,9,0) -> Critical | O12: Home Office
C13: 5168-2 | D13: =VLOOKUP(C13,[1]Orders!$A$5:$W$1043,3,0) -> Christy Brittain | E13: =VLOOKUP(C13,[1]Orders!$A$5:$W$1043,23,0) -> 111.62 | F13: =VLOOKUP(C13,[1]Orders!$A$5:$W$1043,5,0) -> Sydney | G13: =VLOOKUP(C13,[1]Orders!$A$5:$W$1043,5,0) -> Sydney | H13: =VLOOKUP(C13,[1]Orders!$A$5:$W$1043,6,0) -> NSW | I13: =VLOOKUP(C13,[1]Orders!$A$5:$W$1043,7,0) -> Consumer | J13: =VLOOKUP(C13,[1]Orders!$A$5:$W$1043,8,0) -> Mihael Khan | K13: =VLOOKUP(C13,[1]Orders!$A$5:$W$1043,9,0) -> Critical
C14: 5195-1 | D14: =VLOOKUP(C14,[1]Orders!$A$5:$W$1043,3,0) -> Alex Grayson | E14: =VLOOKUP(C14,[1]Orders!$A$5:$W$1043,23,0) -> 33.08 | F14: =VLOOKUP(C14,[1]Orders!$A$5:$W$1043,5,0) -> Sydney | G14: =VLOOKUP(C14,[1]Orders!$A$5:$W$1043,5,0) -> Sydney | H14: =VLOOKUP(C14,[1]Orders!$A$5:$W$1043,6,0) -> NSW | I14: =VLOOKUP(C14,[1]Orders!$A$5:$W$1043,7,0) -> Consumer | J14: =VLOOKUP(C14,[1]Orders!$A$5:$W$1043,8,0) -> Radhya Staples | K14: =VLOOKUP(C14,[1]Orders!$A$5:$W$1043,9,0) -> Medium
C15: 5195-2 | D15: =VLOOKUP(C15,[1]Orders!$A$5:$W$1043,3,0) -> Alex Grayson | E15: =VLOOKUP(C15,[1]Orders!$A$5:$W$1043,23,0) -> 863.04 | F15: =VLOOKUP(C15,[1]Orders!$A$5:$W$1043,5,0) -> Sydney | G15: =VLOOKUP(C15,[1]Orders!$A$5:$W$1043,5,0) -> Sydney | H15: =VLOOKUP(C15,[1]Orders!$A$5:$W$1043,6,0) -> NSW | I15: =VLOOKUP(C15,[1]Orders!$A$5:$W$1043,7,0) -> Consumer | J15: =VLOOKUP(C15,[1]Orders!$A$5:$W$1043,8,0) -> Radhya Staples | K15: =VLOOKUP(C15,[1]Orders!$A$5:$W$1043,9,0) -> Medium
C16: 5268-1 | D16: =VLOOKUP(C16,[1]Orders!$A$5:$W$1043,3,0) -> Stephanie Ulpright | E16: =VLOOKUP(C16,[1]Orders!$A$5:$W$1043,23,0) -> 14.72 | F16: =VLOOKUP(C16,[1]Orders!$A$5:$W$1043,5,0) -> Melbourne | G16: =VLOOKUP(C16,[1]Orders!$A$5:$W$1043,5,0) -> Melbourne | H16: =VLOOKUP(C16,[1]Orders!$A$5:$W$1043,6,0) -> VIC | I16: =VLOOKUP(C16,[1]Orders!$A$5:$W$1043,7,0) -> Consumer | J16: =VLOOKUP(C16,[1]Orders!$A$5:$W$1043,8,0) -> Yvette Biti | K16: =VLOOKUP(C16,[1]Orders!$A$5:$W$1043,9,0) -> Not Specified
C17: 5268-2 | D17: =VLOOKUP(C17,[1]Orders!$A$5:$W$1043,3,0) -> Stephanie Ulpright | E17: =VLOOKUP(C17,[1]Orders!$A$5:$W$1043,23,0) -> 1011.1 | F17: =VLOOKUP(C17,[1]Orders!$A$5:$W$1043,5,0) -> Melbourne | G17: =VLOOKUP(C17,[1]Orders!$A$5:$W$1043,5,0) -> Melbourne | H17: =VLOOKUP(C17,[1]Orders!$A$5:$W$1043,6,0) -> VIC | I17: =VLOOKUP(C17,[1]Orders!$A$5:$W$1043,7,0) -> Consumer | J17: =VLOOKUP(C17,[1]Orders!$A$5:$W$1043,8,0) -> Yvette Biti | K17: =VLOOKUP(C17,[1]Orders!$A$5:$W$1043,9,0) -> Not Specified
C18: 5274-1 | D18: =VLOOKUP(C18,[1]Orders!$A$5:$W$1043,3,0) -> Sylvia Foulston | E18: =VLOOKUP(C18,[1]Orders!$A$5:$W$1043,23,0) -> 7495.56 | F18: =VLOOKUP(C18,[1]Orders!$A$5:$W$1043,5,0) -> Sydney | G18: =VLOOKUP(C18,[1]Orders!$A$5:$W$1043,5,0) -> Sydney | H18: =VLOOKUP(C18,[1]Orders!$A$5:$W$1043,6,0) -> NSW | I18: =VLOOKUP(C18,[1]Orders!$A$5:$W$1043,7,0) -> Corporate | J18: =VLOOKUP(C18,[1]Orders!$A$5:$W$1043,8,0) -> Tina Carlton | K18: =VLOOKUP(C18,[1]Orders!$A$5:$W$1043,9,0) -> Critical
C19: 5274-2 | D19: =VLOOKUP(C19,[1]Orders!$A$5:$W$1043,3,0) -> Sylvia Foulston | E19: =VLOOKUP(C19,[1]Orders!$A$5:$W$1043,23,0) -> 50.9 | F19: =VLOOKUP(C19,[1]Orders!$A$5:$W$1043,5,0) -> Sydney | G19: =VLOOKUP(C19,[1]Orders!$A$5:$W$1043,5,0) -> Sydney | H19: =VLOOKUP(C19,[1]Orders!$A$5:$W$1043,6,0) -> NSW | I19: =VLOOKUP(C19,[1]Orders!$A$5:$W$1043,7,0) -> Corporate | J19: =VLOOKUP(C19,[1]Orders!$A$5:$W$1043,8,0) -> Tina Carlton | K19: =VLOOKUP(C19,[1]Orders!$A$5:$W$1043,9,0) -> Critical
C20: 5335-1 | D20: =VLOOKUP(C20,[1]Orders!$A$5:$W$1043,3,0) -> Patrick Jones | E20: =VLOOKUP(C20,[1]Orders!$A$5:$W$1043,23,0) -> 57.75 | F20: =VLOOKUP(C20,[1]Orders!$A$5:$W$1043,5,0) -> Melbourne | G20: =VLOOKUP(C20,[1]Orders!$A$5:$W$1043,5,0) -> Melbourne | H20: =VLOOKUP(C20,[1]Orders!$A$5:$W$1043,6,0) -> VIC | I20: =VLOOKUP(C20,[1]Orders!$A$5:$W$1043,7,0) -> Home Office | J20: =VLOOKUP(C20,[1]Orders!$A$5:$W$1043,8,0) -> Yvette Biti | K20: =VLOOKUP(C20,[1]Orders!$A$5:$W$1043,9,0) -> Low
C21: 5335-2 | D21: =VLOOKUP(C21,[1]Orders!$A$5:$W$1043,3,0) -> Patrick Jones | E21: =VLOOKUP(C21,[1]Orders!$A$5:$W$1043,23,0) -> 109.02 | F21: =VLOOKUP(C21,[1]Orders!$A$5:$W$1043,5,0) -> Melbourne | G21: =VLOOKUP(C21,[1]Orders!$A$5:$W$1043,5,0) -> Melbourne | H21: =VLOOKUP(C21,[1]Orders!$A$5:$W$1043,6,0) -> VIC | I21: =VLOOKUP(C21,[1]Orders!$A$5:$W$1043,7,0) -> Home Office | J21: =VLOOKUP(C21,[1]Orders!$A$5:$W$1043,8,0) -> Yvette Biti | K21: =VLOOKUP(C21,[1]Orders!$A$5:$W$1043,9,0) -> Low
C22: 5358-1 | D22: =VLOOKUP(C22,[1]Orders!$A$5:$W$1043,3,0) -> Saphhira Shifley | E22: =VLOOKUP(C22,[1]Orders!$A$5:$W$1043,23,0) -> 276.39 | F22: =VLOOKUP(C22,[1]Orders!$A$5:$W$1043,5,0) -> Sydney | G22: =VLOOKUP(C22,[1]Orders!$A$5:$W$1043,5,0) -> Sydney | H22: =VLOOKUP(C22,[1]Orders!$A$5:$W$1043,6,0) -> NSW | I22: =VLOOKUP(C22,[1]Orders!$A$5:$W$1043,7,0) -> Consumer | J22: =VLOOKUP(C22,[1]Orders!$A$5:$W$1043,8,0) -> Preston Senome | K22: =VLOOKUP(C22,[1]Orders!$A$5:$W$1043,9,0) -> Critical
C23: 5358-2 | D23: =VLOOKUP(C23,[1]Orders!$A$5:$W$1043,3,0) -> Saphhira Shifley | E23: =VLOOKUP(C23,[1]Orders!$A$5:$W$1043,23,0) -> 2292.17 | F23: =VLOOKUP(C23,[1]Orders!$A$5:$W$1043,5,0) -> Sydney | G23: =VLOOKUP(C23,[1]Orders!$A$5:$W$1043,5,0) -> Sydney | H23: =VLOOKUP(C23,[1]Orders!$A$5:$W$1043,6,0) -> NSW | I23: =VLOOKUP(C23,[1]Orders!$A$5:$W$1043,7,0) -> Consumer | J23: =VLOOKUP(C23,[1]Orders!$A$5:$W$1043,8,0) -> Preston Senome | K23: =VLOOKUP(C23,[1]Orders!$A$5:$W$1043,9,0) -> Critical
C24: 5367-1 | D24: =VLOOKUP(C24,[1]Orders!$A$5:$W$1043,3,0) -> Anne Pryor | E24: =VLOOKUP(C24,[1]Orders!$A$5:$W$1043,23,0) -> 56.29 | F24: =VLOOKUP(C24,[1]Orders!$A$5:$W$1043,5,0) -> Sydney | G24: =VLOOKUP(C24,[1]Orders!$A$5:$W$1043,5,0) -> Sydney | H24: =VLOOKUP(C24,[1]Orders!$A$5:$W$1043,6,0) -> NSW | I24: =VLOOKUP(C24,[1]Orders!$A$5:$W$1043,7,0) -> Home Office | J24: =VLOOKUP(C24,[1]Orders!$A$5:$W$1043,8,0) -> Aanya Zhang | K24: =VLOOKUP(C24,[1]Orders!$A$5:$W$1043,9,0) -> Medium
... C1044: 6586-1 | D1044: =VLOOKUP(C1044,[1]Orders!$A$5:$W$1043,3,0) -> Theresa Swint | E1044: =VLOOKUP(C1044,[1]Orders!$A$5:$W$1043,23,0) -> 15.4 | F1044: =VLOOKUP(C1044,[1]Orders!$A$5:$W$1043,5,0) -> Melbourne | G1044: =VLOOKUP(C1044,[1]Orders!$A$5:$W$1043,5,0) -> Melbourne | H1044: =VLOOKUP(C1044,[1]Orders!$A$5:$W$1043,6,0) -> VIC | I1044: =VLOOKUP(C1044,[1]Orders!$A$5:$W$1043,7,0) -> Consumer | J1044: =VLOOKUP(C1044,[1]Orders!$A$5:$W$1043,8,0) -> Connor Betts | K1044: =VLOOKUP(C1044,[1]Orders!$A$5:$W$1043,9,0) -> Medium

Sheet Orders
A1: Shipping Data
A3: Order No | B3: Order Date | C3: Customer Name | D3: Address | E3: City | F3: State | G3: Customer Type | H3: Account Manager | I3: Order Priority | J3: Product Name | K3: Product Category | L3: Product Container | M3: Ship Mode | N3: Ship Date | O3: Cost Price | P3: Retail Price | Q3: Order Quantity | R3: Sub Total | S3: Discount % | T3: Discount $ | U3: Order Total | V3: Shipping Cost | W3: Total
A4: Column1 | B4: Column2 | C4: Column3 | D4: Column4 | E4: Column5 | F4: Column6 | G4: Column7 | H4: Column8 | I4: Column9 | J4: Column10 | K4: Column11 | L4: Column12 | M4: Column13 | N4: Column14 | O4: Column15 | P4: Column16 | Q4: Column17 | R4: Column18 | S4: Column19 | T4: Column20 | U4: Column21 | V4: Column22 | W4: Column23
A5: 5071-1 | B5: 41399 | C5: Christopher Schild | D5: 4A Lyons St,Strathfield | E5: Sydney | F5: NSW | G5: Corporate | H5: Tina Carlton | I5: Medium | J5: Laser Neon Mac Format Diskettes, 10/Pack | K5: Technology | L5: Small Pack | M5: Regular Air | N5: 41400 | O5: 1.87 | P5: 8.12 | Q5: 41 | R5: =P5*Q5 -> 332.92 | S5: 0.06 | T5: =R5*S5 -> 19.9752 | U5: =R5-S5 -> 332.86 | V5: 2.83 | W5: =U5+V5 -> 335.69
A6: 5071-2 | B6: 41399 | C6: Christopher Schild | D6: 4A Lyons St,Strathfield | E6: Sydney | F6: NSW | G6: Corporate | H6: Tina Carlton | I6: Medium | J6: Steady Liquid Accent Highlighters | K6: Office Supplies | L6: Wrap Bag | M6: Regular Air | N6: 41400 | O6: 3.47 | P6: 6.68 | Q6: 2 | R6: =P6*Q6 -> 13.36 | S6: 0.01 | T6: =R6*S6 -> 0.1336 | U6: =R6-S6 -> 13.35 | V6: 1.5 | W6: =U6+V6 -> 14.85
A7: 5145-1 | B7: 41454 | C7: Cyma Kinney | D7: Sydney Fish Market, Bank Street, Sydney | E7: Sydney | F7: NSW | G7: Small Business | H7: Phoebe Gour | I7: Low | J7: Alto Memo Cubes | K7: Office Supplies | L7: Wrap Bag | M7: Express Air | N7: 41459 | O7: 3.32 | P7: 5.18 | Q7: 1 | R7: =P7*Q7 -> 5.18 | S7: 0.02 | T7: =R7*S7 -> 0.1036 | U7: =R7-S7 -> 5.16 | V7: 2.04 | W7: =U7+V7 -> 7.2
A8: 5145-2 | B8: 41454 | C8: Cyma Kinney | D8: Sydney Fish Market, Bank Street, Sydney | E8: Sydney | F8: NSW | G8: Small Business | H8: Phoebe Gour | I8: Low | J8: Artisan Hi-Liter Smear-Safe Highlighters | K8: Office Supplies | L8: Wrap Bag | M8: Regular Air | N8: 41458 | O8: 2.98 | P8: 5.84 | Q8: 4 | R8: =P8*Q8 -> 23.36 | S8: 0.09 | T8: =R8*S8 -> 2.1024 | U8: =R8-S8 -> 23.27 | V8: 0.83 | W8: =U8+V8 -> 24.1
A9: 5160-1 | B9: 41460 | C9: Berenike Kampe | D9: 180 High Street,Windsor | E9: Melbourne | F9: VIC | G9: Corporate | H9: Connor Betts | I9: Not Specified | J9: 1726 Digital Answering Machine | K9: Technology | L9: Medium Box | M9: Regular Air | N9: 41462 | O9: 8.82 | P9: 20.99 | Q9: 41 | R9: =P9*Q9 -> 860.59 | S9: 0.02 | T9: =R9*S9 -> 17.2118 | U9: =R9-S9 -> 860.57 | V9: 4.81 | W9: =U9+V9 -> 865.38
A10: 5160-2 | B10: 41460 | C10: Berenike Kampe | D10: 180 High Street,Windsor | E10: Melbourne | F10: VIC | G10: Corporate | H10: Connor Betts | I10: Not Specified | J10: 3Max Organizer Strips | K10: Office Supplies | L10: Small Box | M10: Express Air | N10: 41462 | O10: 3.4 | P10: 5.4 | Q10: 26 | R10: =P10*Q10 -> 140.4 | S10: 0.05 | T10: =R10*S10 -> 7.02 | U10: =R10-S10 -> 140.35 | V10: 7.78 | W10: =U10+V10 -> 148.13
A11: 5168-1 | B11: 41470 | C11: Christy Brittain | D11: Shop 1, 186-190 Church Street,Parramatta;46a Macleay Street,Potts Point | E11: Sydney | F11: NSW | G11: Consumer | H11: Mihael Khan | I11: Critical | J11: Smiths Pen Style Liquid Stix; Assorted (yellow, pink, green, blue, orange), 5/Pack | K11: Office Supplies | L11: Wrap Bag | M11: Regular Air | N11: 41471 | O11: 3.88 | P11: 6.47 | Q11: 20 | R11: =P11*Q11 -> 129.4 | S11: 0.02 | T11: =R11*S11 -> 2.588 | U11: =R11-S11 -> 129.38 | V11: 1.22 | W11: =U11+V11 -> 130.6
A12: 5168-2 | B12: 41470 | C12: Christy Brittain | D12: Shop 1, 186-190 Church Street,Parramatta;46a Macleay Street,Potts Point | E12: Sydney | F12: NSW | G12: Consumer | H12: Mihael Khan | I12: Critical | J12: Steady Liquid Accent Tank-Style Highlighters | K12: Office Supplies | L12: Wrap Bag | M12: Regular Air | N12: 41472 | O12: 1.31 | P12: 2.84 | Q12: 39 | R12: =P12*Q12 -> 110.76 | S12: 0.07 | T12: =R12*S12 -> 7.7532 | U12: =R12-S12 -> 110.69 | V12: 0.93 | W12: =U12+V12 -> 111.62
A13: 5195-1 | B13: 41486 | C13: Alex Grayson | D13: 644 George St,Sydney | E13: Sydney | F13: NSW | G13: Consumer | H13: Radhya Staples | I13: Medium | J13: Artisan Durable Binders | K13: Office Supplies | L13: Small Box | M13: Regular Air | N13: 41487 | O13: 1.84 | P13: 2.88 | Q13: 11 | R13: =P13*Q13 -> 31.68 | S13: 0.09 | T13: =R13*S13 -> 2.8512 | U13: =R13-S13 -> 31.59 | V13: 1.49 | W13: =U13+V13 -> 33.08
A14: 5195-2 | B14: 41486 | C14: Alex Grayson | D14: 644 George St,Sydney | E14: Sydney | F14: NSW | G14: Consumer | H14: Radhya Staples | I14: Medium | J14: Beekin 105-Key Black Keyboard | K14: Technology | L14: Small Box | M14: Regular Air | N14: 41488 | O14: 6.39 | P14: 19.98 | Q14: 43 | R14: =P14*Q14 -> 859.14 | S14: 0.1 | T14: =R14*S14 -> 85.914 | U14: =R14-S14 -> 859.04 | V14: 4 | W14: =U14+V14 -> 863.04
A15: 5268-1 | B15: 41558 | C15: Stephanie Ulpright | D15: 541 Church St ,Richmond | E15: Melbourne | F15: VIC | G15: Consumer | H15: Yvette Biti | I15: Not Specified | J15: Artisan Binder Labels | K15: Office Supplies | L15: Small Box | M15: Regular Air | N15: 41560 | O15: 2.45 | P15: 3.89 | Q15: 2 | R15: =P15*Q15 -> 7.78 | S15: 0.07 | T15: =R15*S15 -> 0.5446 | U15: =R15-S15 -> 7.71 | V15: 7.01 | W15: =U15+V15 -> 14.72
A16: 5268-2 | B16: 41558 | C16: Stephanie Ulpright | D16: 541 Church St ,Richmond | E16: Melbourne | F16: VIC | G16: Consumer | H16: Yvette Biti | I16: Not Specified | J16: Economy Rollaway Files | K16: Office Supplies | L16: Small Box | M16: Regular Air | N16: 41559 | O16: 67.73 | P16: 165.2 | Q16: 6 | R16: =P16*Q16 -> 991.2 | S16: 0.09 | T16: =R16*S16 -> 89.208 | U16: =R16-S16 -> 991.11 | V16: 19.99 | W16: =U16+V16 -> 1011.1
... A1043: 6586-1 | B1043: 42773 | C1043: Theresa Swint | D1043: 240-242 Johnston Street,Fitzroy | E1043: Melbourne | F1043: VIC | G1043: Consumer | H1043: Connor Betts | I1043: Medium | J1043: Binder Clips by OIC | K1043: Office Supplies | L1043: Wrap Bag | M1043: Regular Air | N1043: 42773 | O1043: 0.93 | P1043: 1.48 | Q1043: 10 | R1043: =P1043*Q1043 -> 14.8 | S1043: 0.1 | T1043: =R1043*S1043 -> 1.48 | U1043: =R1043-S1043 -> 14.7 | V1043: 0.7 | W1043: =U1043+V1043 -> 15.4

Sheet list
B4: City | C4: State | D4: Customer Type | E4: Order Priority | F4: Produtct Category | G4: Ship Mode
B5: Sydney | C5: NSW | D5: Corporate | E5: Medium | F5: Technology | G5: Delivery Truck
B6: Sydney | C6: NSW | D6: Corporate | E6: Medium | F6: Office Supplies | G6: Regular Air
B7: Sydney | C7: VIC | D7: Small Business | E7: Low | F7: Furniture | G7: Express Air
B8: Sydney | D8: Consumer | E8: Not Specified
B9: Melbourne | D9: Home Office | E9: Critical

Sheet Salary Sheet &  formula
B2: SALARY SHEET
E3: 0.5 | F3: 0.07 | G3: 0.15 | I3: 0.1
B4: Sl | C4: Name | D4: Basic Salary | E4: HR | F4: TA | G4: MA | H4: GROSS SALARY | I4: PF | J4: NET SALARY | K4: Left | L4: Right | M4: Lower left | O4: Lower Right | P4: Upper Left | Q4: Upper right | R4: Batch | S4: & with string | T4: sumif | U4: sumif plus left | V4: sum ifs | Z4: Multiple Sumifs
B5: 1 | C5: Hasan | D5: 60000 | E5: =$E$3*D5 -> 30000 | F5: =$F$3*D5 -> 4200 | G5: =$G$3*D5 -> 9000 | H5: =G5+F5+E5 -> 43200 | I5: =$I$3*D5 -> 6000 | J5: =H5-I5 -> 37200 | K5: =LEFT(C5,2) -> Ha | L5: =RIGHT(C5,2) -> an | M5: =LOWER(K5) -> ha | N5: 1 | O5: =LOWER(L5) -> an | P5: =UPPER(K5) -> HA | Q5: =UPPER(L5) -> AN | R5: 59 | S5: ="JEE"&"59"&" "&Q5&P5 -> JEE59 ANHA | T5: =SUMIF(M5:M19,"md",N5:N19) -> 45 | U5: =UPPER(LEFT(C5,2)) -> HA | V5: city | W5: c type | X5: amount | Z5: City | AA5: State | AB5: Customer Type | AC5: Order Priority | AD5: Produtct type | AE5: Ship Mode | AF5: total
B6: 2 | C6: Md Najmul Islam | D6: 30000 | E6: =$E$3*D6 -> 15000 | F6: =$F$3*D6 -> 2100 | G6: =$G$3*D6 -> 4500 | H6: =G6+F6+E6 -> 21600 | I6: =$I$3*D6 -> 3000 | J6: =H6-I6 -> 18600 | K6: =LEFT(C6,2) -> Md | L6: =RIGHT(C6,2) -> am | M6: =LOWER(K6) -> md | N6: 2 | O6: =LOWER(L6) -> am | P6: =UPPER(K6) -> MD | Q6: =UPPER(L6) -> AM | R6: 59 | S6: ="JEE"&"59"&" "&Q6&P6 -> JEE59 AMMD | U6: =UPPER(LEFT(C6,2)) -> MD | V6: Sydney | W6: Corporate | X6: =SUMIFS(data!E:E,data!G:G,'Salary Sheet & formula'!V6,data!I:I,'Salary Sheet & formula'!W6) -> 281897.72 | Z6: Sydney | AA6: NSW | AB6: Corporate | AC6: Medium | AD6: Furniture | AE6: Regular Air | AF6: =SUMIFS(Orders!W:W,Orders!E:E,'Salary Sheet & formula'!Z6,Orders!F:F,'Salary Sheet & formula'!AA6,Orders!G:G,'Salary Sheet & formula'!AB6,Orders!I:I,'Salary Sheet & formula'!AC6,Orders!K:K,'Salary Sheet & formula'!AD6,Orders!M:M,'Salary Sheet & formula'!AE6) -> 1942.21
B7: 3 | C7: MD. AMINUL HOQUE | D7: 80000 | E7: =$E$3*D7 -> 40000 | F7: =$F$3*D7 -> 5600 | G7: =$G$3*D7 -> 12000 | H7: =G7+F7+E7 -> 57600 | I7: =$I$3*D7 -> 8000 | J7: =H7-I7 -> 49600 | K7: =LEFT(C7,2) -> MD | L7: =RIGHT(C7,2) -> UE | M7: =LOWER(K7) -> md | N7: 3 | O7: =LOWER(L7) -> ue | P7: =UPPER(K7) -> MD | Q7: =UPPER(L7) -> UE | R7: 59 | S7: ="JEE"&"59"&" "&Q7&P7 -> JEE59 UEMD | U7: =UPPER(LEFT(C7,2)) -> MD | V7: Melbourne | W7: Small Business | X7: =SUMIFS(data!E:E,data!G:G,'Salary Sheet & formula'!V7,data!I:I,'Salary Sheet & formula'!W7) -> 69210.74
B8: 4 | C8: MD. Nasif Shahriar | D8: 50000 | E8: =$E$3*D8 -> 25000 | F8: =$F$3*D8 -> 3500 | G8: =$G$3*D8 -> 7500 | H8: =G8+F8+E8 -> 36000 | I8: =$I$3*D8 -> 5000 | J8: =H8-I8 -> 31000 | K8: =LEFT(C8,2) -> MD | L8: =RIGHT(C8,2) -> ar | M8: =LOWER(K8) -> md | N8: 4 | O8: =LOWER(L8) -> ar | P8: =UPPER(K8) -> MD | Q8: =UPPER(L8) -> AR | R8: 59 | S8: ="JEE"&"59"&" "&Q8&P8 -> JEE59 ARMD | U8: =UPPER(LEFT(C8,2)) -> MD | V8: Sydney | W8: Consumer | X8: =SUMIFS(data!E:E,data!G:G,'Salary Sheet & formula'!V8,data!I:I,'Salary Sheet & formula'!W8) -> 135968.49
B9: 5 | C9: Md. Rabiul Islam | D9: 20000 | E9: =$E$3*D9 -> 10000 | F9: =$F$3*D9 -> 1400 | G9: =$G$3*D9 -> 3000 | H9: =G9+F9+E9 -> 14400 | I9: =$I$3*D9 -> 2000 | J9: =H9-I9 -> 12400 | K9: =LEFT(C9,2) -> Md | L9: =RIGHT(C9,2) -> am | M9: =LOWER(K9) -> md | N9: 5 | O9: =LOWER(L9) -> am | P9: =UPPER(K9) -> MD | Q9: =UPPER(L9) -> AM | R9: 59 | S9: ="JEE"&"59"&" "&Q9&P9 -> JEE59 AMMD | U9: =UPPER(LEFT(C9,2)) -> MD | V9: Melbourne | W9: Home Office | X9: =SUMIFS(data!E:E,data!G:G,'Salary Sheet & formula'!V9,data!I:I,'Salary Sheet & formula'!W9) -> 32110.81
B10: 6 | C10: MD. RAFIQUL ISLAM RAZU | D10: 40000 | E10: =$E$3*D10 -> 20000 | F10: =$F$3*D10 -> 2800 | G10: =$G$3*D10 -> 6000 | H10: =G10+F10+E10 -> 28800 | I10: =$I$3*D10 -> 4000 | J10: =H10-I10 -> 24800 | K10: =LEFT(C10,2) -> MD | L10: =RIGHT(C10,2) -> ZU | M10: =LOWER(K10) -> md | N10: 6 | O10: =LOWER(L10) -> zu | P10: =UPPER(K10) -> MD | Q10: =UPPER(L10) -> ZU | R10: 59 | S10: ="JEE"&"59"&" "&Q10&P10 -> JEE59 ZUMD | U10: =UPPER(LEFT(C10,2)) -> MD | X10: =SUMIFS(data!E:E,data!G:G,'Salary Sheet & formula'!V10,data!I:I,'Salary Sheet & formula'!W10) -> 0
B11: 7 | C11: MD. RAJU AHMED | D11: 20000 | E11: =$E$3*D11 -> 10000 | F11: =$F$3*D11 -> 1400 | G11: =$G$3*D11 -> 3000 | H11: =G11+F11+E11 -> 14400 | I11: =$I$3*D11 -> 2000 | J11: =H11-I11 -> 12400 | K11: =LEFT(C11,2) -> MD | L11: =RIGHT(C11,2) -> ED | M11: =LOWER(K11) -> md | N11: 7 | O11: =LOWER(L11) -> ed | P11: =UPPER(K11) -> MD | Q11: =UPPER(L11) -> ED | R11: 59 | S11: ="JEE"&"59"&" "&Q11&P11 -> JEE59 EDMD | U11: =UPPER(LEFT(C11,2)) -> MD | X11: =SUMIFS(data!E:E,data!G:G,'Salary Sheet & formula'!V11,data!I:I,'Salary Sheet & formula'!W11) -> 0
B12: 8 | C12: MD. SANAULLA | D12: 10000 | E12: =$E$3*D12 -> 5000 | F12: =$F$3*D12 -> 700 | G12: =$G$3*D12 -> 1500 | H12: =G12+F12+E12 -> 7200 | I12: =$I$3*D12 -> 1000 | J12: =H12-I12 -> 6200 | K12: =LEFT(C12,2) -> MD | L12: =RIGHT(C12,2) -> LA | M12: =LOWER(K12) -> md | N12: 8 | O12: =LOWER(L12) -> la | P12: =UPPER(K12) -> MD | Q12: =UPPER(L12) -> LA | R12: 59 | S12: ="JEE"&"59"&" "&Q12&P12 -> JEE59 LAMD | U12: =UPPER(LEFT(C12,2)) -> MD | X12: =SUMIFS(data!E:E,data!G:G,'Salary Sheet & formula'!V12,data!I:I,'Salary Sheet & formula'!W12) -> 0
B13: 9 | C13: Md. Towhidul Alam | D13: 70000 | E13: =$E$3*D13 -> 35000 | F13: =$F$3*D13 -> 4900 | G13: =$G$3*D13 -> 10500 | H13: =G13+F13+E13 -> 50400 | I13: =$I$3*D13 -> 7000 | J13: =H13-I13 -> 43400 | K13: =LEFT(C13,2) -> Md | L13: =RIGHT(C13,2) -> am | M13: =LOWER(K13) -> md | N13: 9 | O13: =LOWER(L13) -> am | P13: =UPPER(K13) -> MD | Q13: =UPPER(L13) -> AM | R13: 59 | S13: ="JEE"&"59"&" "&Q13&P13 -> JEE59 AMMD | U13: =UPPER(LEFT(C13,2)) -> MD | X13: =SUMIFS(data!E:E,data!G:G,'Salary Sheet & formula'!V13,data!I:I,'Salary Sheet & formula'!W13) -> 0
B14: 10 | C14: Md.Kutub Uddin | D14: 50000 | E14: =$E$3*D14 -> 25000 | F14: =$F$3*D14 -> 3500 | G14: =$G$3*D14 -> 7500 | H14: =G14+F14+E14 -> 36000 | I14: =$I$3*D14 -> 5000 | J14: =H14-I14 -> 31000 | K14: =LEFT(C14,2) -> Md | L14: =RIGHT(C14,2) -> in | M14: =LOWER(K14) -> md | N14: 1 | O14: =LOWER(L14) -> in | P14: =UPPER(K14) -> MD | Q14: =UPPER(L14) -> IN | R14: 59 | S14: ="JEE"&"59"&" "&Q14&P14 -> JEE59 INMD | U14: =UPPER(LEFT(C14,2)) -> MD | X14: =SUMIFS(data!E:E,data!G:G,'Salary Sheet & formula'!V14,data!I:I,'Salary Sheet & formula'!W14) -> 0
B15: 11 | C15: Mostofa Aminur Rashid | D15: 40000 | E15: =$E$3*D15 -> 20000 | F15: =$F$3*D15 -> 2800 | G15: =$G$3*D15 -> 6000 | H15: =G15+F15+E15 -> 28800 | I15: =$I$3*D15 -> 4000 | J15: =H15-I15 -> 24800 | K15: =LEFT(C15,2) -> Mo | L15: =RIGHT(C15,2) -> id | M15: =LOWER(K15) -> mo | N15: 11 | O15: =LOWER(L15) -> id | P15: =UPPER(K15) -> MO | Q15: =UPPER(L15) -> ID | R15: 59 | S15: ="JEE"&"59"&" "&Q15&P15 -> JEE59 IDMO | U15: =UPPER(LEFT(C15,2)) -> MO | X15: =SUMIFS(data!E:E,data!G:G,'Salary Sheet & formula'!V15,data!I:I,'Salary Sheet & formula'!W15) -> 0
B16: 12 | C16: NAYAMUL LSLAM | D16: 70000 | E16: =$E$3*D16 -> 35000 | F16: =$F$3*D16 -> 4900 | G16: =$G$3*D16 -> 10500 | H16: =G16+F16+E16 -> 50400 | I16: =$I$3*D16 -> 7000 | J16: =H16-I16 -> 43400 | K16: =LEFT(C16,2) -> NA | L16: =RIGHT(C16,2) -> AM | M16: =LOWER(K16) -> na | N16: 12 | O16: =LOWER(L16) -> am | P16: =UPPER(K16) -> NA | Q16: =UPPER(L16) -> AM | R16: 59 | S16: ="JEE"&"59"&" "&Q16&P16 -> JEE59 AMNA | U16: =UPPER(LEFT(C16,2)) -> NA | X16: =SUMIFS(data!E:E,data!G:G,'Salary Sheet & formula'!V16,data!I:I,'Salary Sheet & formula'!W16) -> 0
B17: 13 | C17: Nusrat Jahan | D17: 30000 | E17: =$E$3*D17 -> 15000 | F17: =$F$3*D17 -> 2100 | G17: =$G$3*D17 -> 4500 | H17: =G17+F17+E17 -> 21600 | I17: =$I$3*D17 -> 3000 | J17: =H17-I17 -> 18600 | K17: =LEFT(C17,2) -> Nu | L17: =RIGHT(C17,2) -> an | M17: =LOWER(K17) -> nu | N17: 13 | O17: =LOWER(L17) -> an | P17: =UPPER(K17) -> NU | Q17: =UPPER(L17) -> AN | R17: 59 | S17: ="JEE"&"59"&" "&Q17&P17 -> JEE59 ANNU | U17: =UPPER(LEFT(C17,2)) -> NU | X17: =SUMIFS(data!E:E,data!G:G,'Salary Sheet & formula'!V17,data!I:I,'Salary Sheet & formula'!W17) -> 0
B18: 14 | C18: Shabab Ahmed | D18: 10000 | E18: =$E$3*D18 -> 5000 | F18: =$F$3*D18 -> 700 | G18: =$G$3*D18 -> 1500 | H18: =G18+F18+E18 -> 7200 | I18: =$I$3*D18 -> 1000 | J18: =H18-I18 -> 6200 | K18: =LEFT(C18,2) -> Sh | L18: =RIGHT(C18,2) -> ed | M18: =LOWER(K18) -> sh | N18: 14 | O18: =LOWER(L18) -> ed | P18: =UPPER(K18) -> SH | Q18: =UPPER(L18) -> ED | R18: 59 | S18: ="JEE"&"59"&" "&Q18&P18 -> JEE59 EDSH | U18: =UPPER(LEFT(C18,2)) -> SH | X18: =SUMIFS(data!E:E,data!G:G,'Salary Sheet & formula'!V18,data!I:I,'Salary Sheet & formula'!W18) -> 0
B19: 15 | C19: Shamima Nasrin | D19: 60000 | E19: =$E$3*D19 -> 30000 | F19: =$F$3*D19 -> 4200 | G19: =$G$3*D19 -> 9000 | H19: =G19+F19+E19 -> 43200 | I19: =$I$3*D19 -> 6000 | J19: =H19-I19 -> 37200 | K19: =LEFT(C19,2) -> Sh | L19: =RIGHT(C19,2) -> in | M19: =LOWER(K19) -> sh | N19: 15 | O19: =LOWER(L19) -> in | P19: =UPPER(K19) -> SH | Q19: =UPPER(L19) -> IN | R19: 59 | S19: ="JEE"&"59"&" "&Q19&P19 -> JEE59 INSH | U19: =UPPER(LEFT(C19,2)) -> SH | X19: =SUMIFS(data!E:E,data!G:G,'Salary Sheet & formula'!V19,data!I:I,'Salary Sheet & formula'!W19) -> 0
B20: Total | C20: =COUNTA(C5:C19) -> 15 | D20: =SUM(D5:D19) -> 640000 | E20: =SUM(E5:E19) -> 320000 | F20: =SUM(F5:F19) -> 44800 | G20: =SUM(G5:G19) -> 96000 | H20: =SUM(H5:H19) -> 460800 | I20: =SUM(I5:I19) -> 64000 | J20: =SUM(J5:J19) -> 396800
C22: Minimum | D22: =MIN(D5:D19) -> 10000 | E22: =MIN(E5:E19) -> 5000 | F22: =MIN(F5:F19) -> 700 | G22: =MIN(G5:G19) -> 1500 | H22: =MIN(H5:H19) -> 7200 | I22: =MIN(I5:I19) -> 1000 | J22: =MIN(J5:J19) -> 6200
C23: Maximum | D23: =MAX(D5:D19) -> 80000 | E23: =MAX(E5:E19) -> 40000 | F23: =MAX(F5:F19) -> 5600 | G23: =MAX(G5:G19) -> 12000 | H23: =MAX(H5:H19) -> 57600 | I23: =MAX(I5:I19) -> 8000 | J23: =MAX(J5:J19) -> 49600
C24: Average | D24: =AVERAGE(D5:D19) -> 42666.667 | E24: =AVERAGE(E5:E19) -> 21333.333 | F24: =AVERAGE(F5:F19) -> 2986.6667 | G24: =AVERAGE(G5:G19) -> 6400 | H24: =AVERAGE(H5:H19) -> 30720 | I24: =AVERAGE(I5:I19) -> 4266.6667 | J24: =AVERAGE(J5:J19) -> 26453.333
C25: Total | D25: =SUM(D5:D19) -> 640000 | E25: =SUM(E5:E19) -> 320000 | F25: =SUM(F5:F19) -> 44800 | G25: =SUM(G5:G19) -> 96000 | H25: =SUM(H5:H19) -> 460800 | I25: =SUM(I5:I19) -> 64000 | J25: =SUM(J5:J19) -> 396800
C26: Counta | D26: =COUNTA(D5:D19) -> 15 | E26: =COUNTA(E5:E19) -> 15 | F26: =COUNTA(F5:F19) -> 15 | G26: =COUNTA(G5:G19) -> 15 | H26: =COUNTA(H5:H19) -> 15 | I26: =COUNTA(I5:I19) -> 15 | J26: =COUNTA(J5:J19) -> 15
C27: count | D27: =COUNT(D5:D19) -> 15 | E27: =COUNT(E5:E19) -> 15 | F27: =COUNT(F5:F19) -> 15 | G27: =COUNT(G5:G19) -> 15 | H27: =COUNT(H5:H19) -> 15 | I27: =COUNT(I5:I19) -> 15 | J27: =COUNT(J5:J19) -> 15
C28: blank | D28: =COUNTBLANK(D5:D19) -> 0 | E28: =COUNTBLANK(E5:E19) -> 0 | F28: =COUNTBLANK(F5:F19) -> 0 | G28: =COUNTBLANK(G5:G19) -> 0 | H28: =COUNTBLANK(H5:H19) -> 0 | I28: =COUNTBLANK(I5:I19) -> 0 | J28: =COUNTBLANK(J5:J19) -> 0

Sheet 23-jan-2024
B1: JEE 59
B2: SL | C2: ID | D2: Name | E2: DOB | F2: Phone | G2: Email | H2: Salary | I2: % | J2: Total
B3: 1 | C3: 1281148 | D3: MD. SANAULLA | E3: 15/02/1997 | F3: 01303246215 | G3: sanaullah1997215@gmail.com | H3: 10000 | I3: 0.5 | J3: =H3*I3 -> 5000 | L3: 0.68888889
B4: 2 | C4: 1281250 | D4: MD. RAJU AHMED | E4: 17/09/1996 | F4: 01624960378 | G4: tamimahmedraju@gmail.com | H4: 20000 | I4: 0.6 | J4: =H4*I4 -> 12000
B5: 3 | C5: 1281305 | D5: Md Najmul Islam | E5: 16/06/1999 | F5: 01790349310 | G5: thatsnajmul@gmail.com | H5: 30000 | I5: 0.05 | J5: =H5*I5 -> 1500
B6: 4 | C6: 1281332 | D6: Mostofa Aminur Rashid | E6: 14/10/1999 | F6: 01521417316 | G6: mostofa.aminur.rezvi@gmail.com | H6: 40000 | I6: 0.1 | J6: =H6*I6 -> 4000
B7: 5 | C7: 1281514 | D7: Md.Kutub Uddin | E7: 13/08/2000 | F7: 01763001787 | G7: mdkutub150@gmail.com | H7: 50000 | I7: 0.2 | J7: =H7*I7 -> 10000
B8: 6 | C8: 1281521 | D8: Shamima Nasrin | E8: 20/12/1996 | F8: 01838020680 | G8: nasrin05shamima@gmail.com | H8: 60000 | I8: 0.3 | J8: =H8*I8 -> 18000
B9: 7 | C9: 1281524 | D9: Md. Towhidul Alam | E9: 17/12/1998 | F9: 01767515057 | G9: alammdtowhidul9@gmail.com | H9: 70000 | I9: 0.4 | J9: =H9*I9 -> 28000
B10: 8 | C10: 1281525 | D10: MD. AMINUL HOQUE | E10: 35132 | F10: 01717947670 | G10: nusunusu111@gmail.com | H10: 80000 | I10: 0.5 | J10: =H10*I10 -> 40000
B11: 9 | C11: 1281539 | D11: Shabab Ahmed | E11: 28/09/2000 | F11: 01710295968 | G11: sabab239.1@gmail.com | H11: 10000 | I11: 0.6 | J11: =H11*I11 -> 6000
B12: 10 | C12: 1281573 | D12: Md. Rabiul Islam | E12: 15/05/1997 | F12: 01780568877 | G12: rbiulislam10571@gmail.com | H12: 20000 | I12: 0.05 | J12: =H12*I12 -> 1000
B13: 11 | C13: 1281608 | D13: Nusrat Jahan | E13: 14/10/2000 | F13: 01847307407 | G13: n.j.naima222@gmail.com | H13: 30000 | I13: 0.02 | J13: =H13*I13 -> 600
B14: 12 | C14: 1281656 | D14: MD. RAFIQUL ISLAM RAZU | E14: 36136 | F14: 01775805206 | G14: rafiqulislamrazu977@gmail.com | H14: 40000 | I14: 0.3 | J14: =H14*I14 -> 12000
B15: 13 | C15: 1281661 | D15: MD. Nasif Shahriar | E15: 36172 | F15: 01784054171 | G15: shahriyarnirjash1996@gmail.com | H15: 50000 | I15: 0.8 | J15: =H15*I15 -> 40000
B16: 14 | C16: 1281714 | D16: Hasan | E16: 35796 | F16: 01813058381 | H16: 60000 | I16: 0.04 | J16: =H16*I16 -> 2400
B17: 15 | C17: 1281745 | D17: NAYAMUL LSLAM | E17: 34760 | F17: 01323276407 | G17: nayamulislam@gmail.com | H17: 70000 | I17: 0.04 | J17: =H17*I17 -> 2800
B18: Total | D18: =COUNTA(D3:D17) -> 15 | E18: =COUNTA(E3:E17) -> 15 | F18: =COUNTA(F3:F17) -> 15 | G18: =COUNTA(G3:G17) -> 14 | H18: =SUM(H3:H17) -> 640000 | I18: =SUM(I3:I17) -> 4.5 | J18: =SUM(J3:J17) -> 183300
C24: pvtable
C39: a | D39: 40
C40: b | D40: 50
C41: c | D41: 38

Sheet 24-jan-2024

Sheet chart
A3: Row Labels | B3: Sum of Email
A4: Hasan | B4: 60000
A5: Md Najmul Islam | B5: 30000
A6: MD. AMINUL HOQUE | B6: 80000
A7: MD. Nasif Shahriar | B7: 50000
A8: Md. Rabiul Islam | B8: 20000
A9: MD. RAFIQUL ISLAM RAZU | B9: 40000
A10: MD. RAJU AHMED | B10: 20000
A11: MD. SANAULLA | B11: 10000
A12: Md. Towhidul Alam | B12: 70000
A13: Md.Kutub Uddin | B13: 50000
A14: Mostofa Aminur Rashid | B14: 40000
A15: NAYAMUL LSLAM | B15: 70000
... A19: Grand Total | B19: 640000

Sheet calc
D2: SL | E2: ID | F2: Name | G2: DOB | H2: Phone | I2: Email | J2: Salary | K2: % | L2: Total
D3: 1281148 | E3: MD. SANAULLA | F3: 15/02/1997 | G3: 01303246215 | H3: sanaullah1997215@gmail.com | I3: 10000 | J3: 0.5 | K3: =I3*J3 -> 5000
D4: 1281250 | E4: MD. RAJU AHMED | F4: 17/09/1996 | G4: 01624960378 | H4: tamimahmedraju@gmail.com | I4: 20000 | J4: 0.6 | K4: =I4*J4 -> 12000
D5: 1281305 | E5: Md Najmul Islam | F5: 16/06/1999 | G5: 01790349310 | H5: thatsnajmul@gmail.com | I5: 30000 | J5: 0.05 | K5: =I5*J5 -> 1500
D6: 1281332 | E6: Mostofa Aminur Rashid | F6: 14/10/1999 | G6: 01521417316 | H6: mostofa.aminur.rezvi@gmail.com | I6: 40000 | J6: 0.1 | K6: =I6*J6 -> 4000
D7: 1281514 | E7: Md.Kutub Uddin | F7: 13/08/2000 | G7: 01763001787 | H7: mdkutub150@gmail.com | I7: 50000 | J7: 0.2 | K7: =I7*J7 -> 10000
D8: 1281521 | E8: Shamima Nasrin | F8: 20/12/1996 | G8: 01838020680 | H8: nasrin05shamima@gmail.com | I8: 60000 | J8: 0.3 | K8: =I8*J8 -> 18000
D9: 1281524 | E9: Md. Towhidul Alam | F9: 17/12/1998 | G9: 01767515057 | H9: alammdtowhidul9@gmail.com | I9: 70000 | J9: 0.4 | K9: =I9*J9 -> 28000
D10: 1281525 | E10: MD. AMINUL HOQUE | F10: 35132 | G10: 01717947670 | H10: nusunusu111@gmail.com | I10: 80000 | J10: 0.5 | K10: =I10*J10 -> 40000
D11: 1281539 | E11: Shabab Ahmed | F11: 28/09/2000 | G11: 01710295968 | H11: sabab239.1@gmail.com | I11: 10000 | J11: 0.6 | K11: =I11*J11 -> 6000
D12: 1281573 | E12: Md. Rabiul Islam | F12: 15/05/1997 | G12: 01780568877 | H12: rbiulislam10571@gmail.com | I12: 20000 | J12: 0.05 | K12: =I12*J12 -> 1000
D13: 1281608 | E13: Nusrat Jahan | F13: 14/10/2000 | G13: 01847307407 | H13: n.j.naima222@gmail.com | I13: 30000 | J13: 0.02 | K13: =I13*J13 -> 600
D14: 1281656 | E14: MD. RAFIQUL ISLAM RAZU | F14: 36136 | G14: 01775805206 | H14: rafiqulislamrazu977@gmail.com | I14: 40000 | J14: 0.3 | K14: =I14*J14 -> 12000
D15: 1281661 | E15: MD. Nasif Shahriar | F15: 36172 | G15: 01784054171 | H15: shahriyarnirjash1996@gmail.com | I15: 50000 | J15: 0.8 | K15: =I15*J15 -> 40000
D16: 1281714 | E16: Hasan | F16: 35796 | G16: 01813058381 | I16: 60000 | J16: 0.04 | K16: =I16*J16 -> 2400
D17: 1281745 | E17: NAYAMUL LSLAM | F17: 34760 | G17: 01323276407 | H17: nayamulislam@gmail.com | I17: 70000 | J17: 0.04 | K17: =I17*J17 -> 2800
